Metadata-Version: 2.1
Name: azure-devops-pyspark
Version: 0.0.1
Summary: A productive library to extract data from Azure Devops and apply agile metrics.
Home-page: UNKNOWN
Author: Guilherme Silva dos Santos
Author-email: gusantos.ok@gmail.com
License: GNU General Public License v3.0
Keywords: Azure AzureDevops WorkItems PySpark Agile
Platform: UNKNOWN
License-File: LICENSE.txt
